openagentkit/__init__.py
openagentkit/core/__init__.py
openagentkit/core/_types/__init__.py
openagentkit/core/_types/named_byte_io.py
openagentkit/core/handlers/__init__.py
openagentkit/core/handlers/tool_handler.py
openagentkit/core/interfaces/__init__.py
openagentkit/core/interfaces/async_base_embedding_model.py
openagentkit/core/interfaces/async_base_executor.py
openagentkit/core/interfaces/async_base_llm_model.py
openagentkit/core/interfaces/async_reranker_model.py
openagentkit/core/interfaces/base_chunker.py
openagentkit/core/interfaces/base_embedding_model.py
openagentkit/core/interfaces/base_executor.py
openagentkit/core/interfaces/base_llm_model.py
openagentkit/core/interfaces/base_reranker_model.py
openagentkit/core/interfaces/base_speech_model.py
openagentkit/core/interfaces/base_tool_handler.py
openagentkit/core/models/__init__.py
openagentkit/core/models/io/__init__.py
openagentkit/core/models/io/embeddings.py
openagentkit/core/models/io/reranking.py
openagentkit/core/models/payloads/__init__.py
openagentkit/core/models/payloads/realtime_payload.py
openagentkit/core/models/responses/__init__.py
openagentkit/core/models/responses/embedding_response.py
openagentkit/core/models/responses/openagent_response.py
openagentkit/core/models/responses/openagent_stream_response.py
openagentkit/core/models/responses/reranking_response.py
openagentkit/core/models/responses/usage_responses.py
openagentkit/core/models/tool_responses/__init__.py
openagentkit/core/models/tool_responses/tool_response.py
openagentkit/core/models/tool_responses/weather_response.py
openagentkit/core/utils/__init__.py
openagentkit/core/utils/audio_utils.py
openagentkit/core/utils/tool_wrapper.py
openagentkit/modules/__init__.py
openagentkit/modules/chunking/__init__.py
openagentkit/modules/chunking/character_text_chunker.py
openagentkit/modules/chunking/recursive_text_chunker.py
openagentkit/modules/chunking/semantic_text_chunker.py
openagentkit/modules/database/__init__.py
openagentkit-0.1.0.dev19.dist-info/licenses/LICENSE
openagentkit-0.1.0.dev19.dist-info/METADATA
openagentkit-0.1.0.dev19.dist-info/WHEEL
openagentkit-0.1.0.dev19.dist-info/top_level.txt
openagentkit-0.1.0.dev19.dist-info/RECORD
