Metadata-Version: 2.4
Name: openagentkit
Version: 0.1.0.dev19
Summary: An open-source framework for building and deploying AI agents.
Home-page: https://github.com/JustKiet/openagentkit
Author: Kiet Do
Author-email: kietdohuu@gmail.com
License: Apache-2.0
Project-URL: Bug Reports, https://github.com/JustKiet/openagentkit/issues
Project-URL: Source, https://github.com/JustKiet/openagentkit
Project-URL: Documentation, https://github.com/JustKiet/openagentkit#readme
Keywords: AI,agents,open-source,llm,tools,executors
Classifier: Development Status :: 3 - Alpha
Classifier: Intended Audience :: Developers
Classifier: Topic :: Software Development :: Libraries :: Python Modules
Classifier: Topic :: Scientific/Engineering :: Artificial Intelligence
Classifier: Programming Language :: Python :: 3
Classifier: Programming Language :: Python :: 3.12
Classifier: License :: OSI Approved :: Apache Software License
Classifier: Operating System :: OS Independent
Requires-Python: >=3.11
License-File: LICENSE
Requires-Dist: aiohappyeyeballs==2.6.1
Requires-Dist: aiohttp==3.11.18
Requires-Dist: aiolimiter==1.2.1
Requires-Dist: aiosignal==1.3.2
Requires-Dist: annotated-types==0.7.0
Requires-Dist: anyio==4.9.0
Requires-Dist: attrs==25.3.0
Requires-Dist: certifi==2025.1.31
Requires-Dist: charset-normalizer==3.4.1
Requires-Dist: click==8.1.8
Requires-Dist: distro==1.9.0
Requires-Dist: filelock==3.18.0
Requires-Dist: frozenlist==1.6.0
Requires-Dist: fsspec==2025.3.2
Requires-Dist: grpcio==1.67.1
Requires-Dist: h11==0.14.0
Requires-Dist: hf-xet==1.1.0
Requires-Dist: httpcore==1.0.8
Requires-Dist: httpx==0.28.1
Requires-Dist: httpx-sse==0.4.0
Requires-Dist: huggingface-hub==0.31.1
Requires-Dist: idna==3.10
Requires-Dist: jiter==0.9.0
Requires-Dist: loguru==0.7.3
Requires-Dist: markdown-it-py==3.0.0
Requires-Dist: mcp[cli]==1.6.0
Requires-Dist: mdurl==0.1.2
Requires-Dist: milvus-lite==2.4.12
Requires-Dist: multidict==6.4.3
Requires-Dist: numpy==2.2.4
Requires-Dist: openai==1.74.0
Requires-Dist: packaging==25.0
Requires-Dist: pandas==2.2.3
Requires-Dist: pillow==11.2.1
Requires-Dist: pip-chill==1.0.3
Requires-Dist: propcache==0.3.1
Requires-Dist: protobuf==6.30.2
Requires-Dist: pydantic==2.11.3
Requires-Dist: pydantic-core==2.33.1
Requires-Dist: pydantic-settings==2.8.1
Requires-Dist: pygments==2.19.1
Requires-Dist: pymilvus==2.5.6
Requires-Dist: python-dateutil==2.9.0.post0
Requires-Dist: python-dotenv==1.1.0
Requires-Dist: pytz==2025.2
Requires-Dist: pyyaml==6.0.2
Requires-Dist: regex==2024.11.6
Requires-Dist: requests==2.32.3
Requires-Dist: rich==14.0.0
Requires-Dist: scipy==1.15.2
Requires-Dist: shellingham==1.5.4
Requires-Dist: six==1.17.0
Requires-Dist: sniffio==1.3.1
Requires-Dist: sse-starlette==2.2.1
Requires-Dist: starlette==0.46.2
Requires-Dist: tenacity==9.1.2
Requires-Dist: tiktoken==0.9.0
Requires-Dist: tokenizers==0.21.1
Requires-Dist: tqdm==4.67.1
Requires-Dist: typer==0.15.2
Requires-Dist: typing-extensions==4.13.2
Requires-Dist: typing-inspection==0.4.0
Requires-Dist: tzdata==2025.2
Requires-Dist: ujson==5.10.0
Requires-Dist: urllib3==2.4.0
Requires-Dist: uvicorn==0.34.2
Requires-Dist: voyageai==0.3.2
Requires-Dist: websockets==15.0.1
Requires-Dist: yarl==1.20.0
Dynamic: author
Dynamic: author-email
Dynamic: classifier
Dynamic: description
Dynamic: description-content-type
Dynamic: home-page
Dynamic: keywords
Dynamic: license
Dynamic: license-file
Dynamic: project-url
Dynamic: requires-dist
Dynamic: requires-python
Dynamic: summary
